seedfarmer/__init__.py
seedfarmer/__main__.py
seedfarmer/__metadata__.py
seedfarmer/checksum.py
seedfarmer/error_handler.py
seedfarmer/input_validators.py
seedfarmer/messages.py
seedfarmer/output_utils.py
seedfarmer/utils.py
seedfarmer/cli_groups/__init__.py
seedfarmer/cli_groups/_bootstrap_group.py
seedfarmer/cli_groups/_bundle_group.py
seedfarmer/cli_groups/_init_group.py
seedfarmer/cli_groups/_list_group.py
seedfarmer/cli_groups/_manage_metadata_group.py
seedfarmer/cli_groups/_project_group.py
seedfarmer/cli_groups/_remove_group.py
seedfarmer/cli_groups/_seedkit_group.py
seedfarmer/cli_groups/_store_group.py
seedfarmer/cli_groups/_taint_group.py
seedfarmer/commands/__init__.py
seedfarmer/commands/_bootstrap_commands.py
seedfarmer/commands/_cfn_seedkit.py
seedfarmer/commands/_deployment_commands.py
seedfarmer/commands/_network_parameter_commands.py
seedfarmer/commands/_parameter_commands.py
seedfarmer/commands/_project_policy_commands.py
seedfarmer/commands/_runtimes.py
seedfarmer/commands/_seedkit_commands.py
seedfarmer/commands/_stack_commands.py
seedfarmer/deployment/__init__.py
seedfarmer/deployment/codebuild_local.py
seedfarmer/deployment/codebuild_remote.py
seedfarmer/deployment/deploy_base.py
seedfarmer/deployment/deploy_factory.py
seedfarmer/deployment/deploy_local.py
seedfarmer/deployment/deploy_remote.py
seedfarmer/errors/__init__.py
seedfarmer/errors/seedfarmer_errors.py
seedfarmer/mgmt/__init__.py
seedfarmer/mgmt/archive_support.py
seedfarmer/mgmt/build_info.py
seedfarmer/mgmt/bundle.py
seedfarmer/mgmt/bundle_support.py
seedfarmer/mgmt/deploy_utils.py
seedfarmer/mgmt/git_support.py
seedfarmer/mgmt/metadata_support.py
seedfarmer/mgmt/module_info.py
seedfarmer/mgmt/module_init.py
seedfarmer/models/__init__.py
seedfarmer/models/_base.py
seedfarmer/models/_deploy_spec.py
seedfarmer/models/_project_spec.py
seedfarmer/models/deploy_responses.py
seedfarmer/models/manifests/__init__.py
seedfarmer/models/manifests/_deployment_manifest.py
seed_farmer-8.0.0.dist-info/METADATA
seed_farmer-8.0.0.dist-info/WHEEL
seed_farmer-8.0.0.dist-info/entry_points.txt
seed_farmer-8.0.0.dist-info/licenses/LICENSE
seed_farmer-8.0.0.dist-info/licenses/NOTICE
seed_farmer-8.0.0.dist-info/licenses/VERSION
seed_farmer-8.0.0.dist-info/RECORD
